login2fa/__init__.py
login2fa/modulo.py
login2fa/setup.py
login2fa-1.0.0.dist-info/licenses/LICENSE
login2fa-1.0.0.dist-info/METADATA
login2fa-1.0.0.dist-info/WHEEL
login2fa-1.0.0.dist-info/top_level.txt
login2fa-1.0.0.dist-info/RECORD
